parglare/__init__.py
parglare/actions.py
parglare/cli.py
parglare/closure.py
parglare/common.py
parglare/exceptions.py
parglare/export.py
parglare/glr.py
parglare/grammar.py
parglare/parser.py
parglare/termui.py
parglare/trees.py
parglare/tables/__init__.py
parglare/tables/persist.py
parglare-0.20.0.dist-info/entry_points.txt
parglare-0.20.0.dist-info/licenses/LICENSE
parglare-0.20.0.dist-info/WHEEL
parglare-0.20.0.dist-info/METADATA
parglare-0.20.0.dist-info/RECORD
