Metadata-Version: 2.4
Name: parglare
Version: 0.20.0
Summary: A pure Python LR/GLR parser
Keywords: parser,lr,glr
Author-email: "Igor R. Dejanović" <igor.dejanovic@gmail.com>
Maintainer-email: "Igor R. Dejanović" <igor.dejanovic@gmail.com>
Requires-Python: >=3.8, <=3.14
Classifier: Development Status :: 4 - Beta
Classifier: Intended Audience :: Developers
Classifier: Intended Audience :: Information Technology
Classifier: Intended Audience :: Science/Research
Classifier: Topic :: Software Development :: Interpreters
Classifier: Topic :: Software Development :: Compilers
Classifier: Topic :: Software Development :: Libraries :: Python Modules
Classifier: License :: OSI Approved :: MIT License
Classifier: Natural Language :: English
Classifier: Programming Language :: Python :: 3
Classifier: Programming Language :: Python :: 3.8
Classifier: Programming Language :: Python :: 3.9
Classifier: Programming Language :: Python :: 3.10
Classifier: Programming Language :: Python :: 3.11
Classifier: Programming Language :: Python :: 3.12
Classifier: Programming Language :: Python :: 3.13
Classifier: Programming Language :: Python :: 3.14
Classifier: Operating System :: OS Independent
License-File: LICENSE
Requires-Dist: click >=7.0, <9.0
Project-URL: Changelog, https://github.com/igordejanovic/parglare/blob/master/CHANGELOG.md
Project-URL: Homepage, https://github.com/igordejanovic/parglare
Project-URL: Repository, https://github.com/igordejanovic/parglare
